pyfrozen/__init__.py
pyfrozen/frozendict.py
pyfrozen/frozenlist.py
pyfrozen-0.2.0.dist-info/LICENSE
pyfrozen-0.2.0.dist-info/WHEEL
pyfrozen-0.2.0.dist-info/METADATA
pyfrozen-0.2.0.dist-info/RECORD
