Metadata-Version: 2.1
Name: pyfrozen
Version: 0.2.0
Summary: Set of collections with ability to freeze their items
Home-page: https://github.com/Gr1N/pyfrozen
License: MIT
Keywords: collections,frozen,freeze
Author: Nikita Grishko
Author-email: gr1n@protonmail.com
Requires-Python: >=3.6,<4.0
Classifier: License :: OSI Approved :: MIT License
Classifier: Programming Language :: Python :: 3
Classifier: Programming Language :: Python :: 3.6
Classifier: Programming Language :: Python :: 3.7
Classifier: Topic :: Software Development :: Libraries :: Python Modules
